Metadata-Version: 2.1
Name: pymb1
Version: 1.0.0
Summary: A telegram bot for all your mirror needs
Home-page: https://github.com/reaitten/pymb1
Author: reaitten
Author-email: wsy0xf2u8@relay.firefox.com
License: UNKNOWN
Project-URL: Bug Tracker, https://github.com/reaitten/pymb1/issues
Platform: UNKNOWN
Classifier: Programming Language :: Python :: 3.8
Classifier: Operating System :: POSIX :: Linux
Classifier: Development Status :: 5 - Production/Stable
Requires-Python: >=3.8.2
License-File: LICENSE
Requires-Dist: requests
Requires-Dist: psutil
Requires-Dist: python-telegram-bot (==12.6.1)
Requires-Dist: google-api-python-client (<1.7.20,>=1.7.11)
Requires-Dist: google-auth-httplib2 (<0.1.0,>=0.0.3)
Requires-Dist: google-auth-oauthlib (<0.10.0,>=0.4.1)
Requires-Dist: aria2p (<0.15.0,>=0.9.0)
Requires-Dist: python-dotenv (>=0.10)
Requires-Dist: tenacity (>=6.0.0)
Requires-Dist: python-magic
Requires-Dist: beautifulsoup4 (<4.8.10,>=4.8.2)
Requires-Dist: Pyrogram (<0.16.10,>=0.16.0)
Requires-Dist: TgCrypto (<1.1.10,>=1.1.1)
Requires-Dist: youtube-dl
Requires-Dist: megasdkrestclient (<1.0.0,>=0.1.1)
